mc_transformers/__init__.py
mc_transformers/data_classes.py
mc_transformers/featuring.py
mc_transformers/mc_transformers.py
mc_transformers/utils_mc.py
mc_transformers/window_examples.py
mc_transformers-0.2.0.dist-info/AUTHORS.rst
mc_transformers-0.2.0.dist-info/LICENSE
mc_transformers-0.2.0.dist-info/METADATA
mc_transformers-0.2.0.dist-info/WHEEL
mc_transformers-0.2.0.dist-info/entry_points.txt
mc_transformers-0.2.0.dist-info/top_level.txt
mc_transformers-0.2.0.dist-info/RECORD
