Metadata-Version: 2.1
Name: mc-transformers
Version: 0.2.0
Summary: Utils to run multiple choice question answering with huggingface transformers
Home-page: https://github.com/geblanco/mc_transformers
Author: Guillermo E. Blanco
Author-email: geblanco@lsi.uned.es
License: Apache Software License 2.0
Keywords: mc_transformers
Platform: UNKNOWN
Classifier: Development Status :: 2 - Pre-Alpha
Classifier: Intended Audience :: Developers
Classifier: License :: OSI Approved :: Apache Software License
Classifier: Natural Language :: English
Classifier: Programming Language :: Python :: 3
Classifier: Programming Language :: Python :: 3.8
Requires-Python: >=3.5
License-File: LICENSE
License-File: AUTHORS.rst
Requires-Dist: transformers
Requires-Dist: torch (==1.9.0)
Requires-Dist: torchvision (==0.10.0)
Requires-Dist: tensorflow (==2.5.0)
Provides-Extra: windowing
Requires-Dist: nltk ; extra == 'windowing'
